pyhazard/__init__.py
rdhazard-0.0.13.dist-info/METADATA
rdhazard-0.0.13.dist-info/WHEEL
rdhazard-0.0.13.dist-info/top_level.txt
rdhazard-0.0.13.dist-info/RECORD
