Metadata-Version: 2.1
Name: rdhazard
Version: 0.0.13
Summary: helper for hazard grabber
Author: rdimo
Author-email: 
